Metadata-Version: 2.1
Name: py-perl5
Version: 2.0.0
Summary: Perl 5 integration for python
Home-page: https://github.com/yacchi/PyPerl5
Author: Yasunori Fujie
Author-email: fuji@dmgw.net
License: Apache License, Version 2.0
Platform: UNKNOWN
